README.rst
setup.py
SASE_hunter/SASE_hunter.py
SASE_hunter/__init__.py
SASE_hunter/__main__.py
SASE_hunter.egg-info/PKG-INFO
SASE_hunter.egg-info/SOURCES.txt
SASE_hunter.egg-info/dependency_links.txt
SASE_hunter.egg-info/requires.txt
SASE_hunter.egg-info/top_level.txt