Metadata-Version: 1.0
Name: SASE-hunter
Version: 0.1.1
Summary: Signatures of Accelerated Somatic Evolution hunter
Home-page: https://github.com/kylessmith/SASE-hunter
Author: Kyle S. Smith, Brent Pedersen
Author-email: kyle.s.smith@ucdenver.edu
License: MIT Licenses
Platform: UNKNOWN
